odoo/addons/sale_report_delivered_subtotal/README.rst
odoo/addons/sale_report_delivered_subtotal/__init__.py
odoo/addons/sale_report_delivered_subtotal/__manifest__.py
odoo/addons/sale_report_delivered_subtotal/i18n/es.po
odoo/addons/sale_report_delivered_subtotal/i18n/it.po
odoo/addons/sale_report_delivered_subtotal/i18n/sale_report_delivered_subtotal.pot
odoo/addons/sale_report_delivered_subtotal/readme/CONTRIBUTORS.rst
odoo/addons/sale_report_delivered_subtotal/readme/DESCRIPTION.rst
odoo/addons/sale_report_delivered_subtotal/readme/USAGE.rst
odoo/addons/sale_report_delivered_subtotal/reports/__init__.py
odoo/addons/sale_report_delivered_subtotal/reports/sale_report.py
odoo/addons/sale_report_delivered_subtotal/static/description/icon.png
odoo/addons/sale_report_delivered_subtotal/static/description/index.html
odoo14_addon_sale_report_delivered_subtotal-14.0.1.0.1.dev6.dist-info/METADATA
odoo14_addon_sale_report_delivered_subtotal-14.0.1.0.1.dev6.dist-info/WHEEL
odoo14_addon_sale_report_delivered_subtotal-14.0.1.0.1.dev6.dist-info/top_level.txt
odoo14_addon_sale_report_delivered_subtotal-14.0.1.0.1.dev6.dist-info/RECORD
